disinheritance/__init__.py
disinheritance/_disinherit.py
disinheritance-1.1.2.dist-info/licenses/LICENSE
disinheritance-1.1.2.dist-info/METADATA
disinheritance-1.1.2.dist-info/WHEEL
disinheritance-1.1.2.dist-info/top_level.txt
disinheritance-1.1.2.dist-info/RECORD
