Metadata-Version: 2.4
Name: disinheritance
Version: 1.1.2
Summary: Direct management of inherited methods/attributes in subclassed object types
Author: Stanton K. Nielson
Project-URL: Homepage, https://github.com/stannielson/Python-Disinheritance
Requires-Python: >=3.10
License-File: LICENSE
Dynamic: license-file
